tinydb_dict/__init__.py
tinydb_dict/py.typed
tinydb_dict-0.1.2.dist-info/WHEEL
tinydb_dict-0.1.2.dist-info/METADATA
tinydb_dict-0.1.2.dist-info/RECORD
