Metadata-Version: 2.1
Name: tinydb-dict
Version: 0.1.2
Summary: Simple dict-like class for TinyDB
Home-page: https://github.com/AliGhahraei/tinydb-dict
License: MIT
Keywords: tinydb
Author: Ali Ghahraei
Author-email: aligf94@gmail.com
Requires-Python: >=3.7,<4.0
Classifier: License :: OSI Approved :: MIT License
Classifier: Programming Language :: Python :: 3
Classifier: Programming Language :: Python :: 3.7
Requires-Dist: tinydb (>=3.13,<4.0)
Project-URL: Repository, https://github.com/AliGhahraei/tinydb-dict
